{
    "profiles": [
        {
            "id": "b396a08",
            "primeiro_nome": "Dante Lima",
            "ultimo_nome": "dos Santos",
            "data_nascimento": "2022-10-05",
            "idade": 2.0,
            "peso": 11.700,
            "sexo": "Masculino",
            "altura": 0.80,
            "cor": "Branco",
            "tipo_sanguineo": "A+",
            "pai_id": 1,
            "mae_id": 2,
            "irmaos_id": []
        },
        {
            "id": "b396a07",
            "primeiro_nome": "André Luiz",
            "ultimo_nome": "Silva Santos",
            "data_nascimento": "1997-06-29",
            "idade": 26.0,
            "peso": 91.0,
            "sexo": "Masculino",
            "altura": 1.67,
            "cor": "Branco",
            "tipo_sanguineo": "A+",
            "pai_id": 3,
            "mae_id": 4,
            "irmaos_id": []
        },
        {
            "id": "b396a06",
            "primeiro_nome": "Milca Regina",
            "ultimo_nome": "Floriano de Lima",
            "data_nascimento": "1996-06-26",
            "idade": 28.0,
            "peso": 62.0,
            "sexo": "Feminino",
            "altura": 1.55,
            "cor": "Preta",
            "tipo_sanguineo": "A+",
            "pai_id": 5,
            "mae_id": 6,
            "irmaos_id": []
        },
        {
            "id": "b396a05",
            "primeiro_nome": "Antonio de Pádua",
            "ultimo_nome": "Silva Santos",
            "data_nascimento": null,
            "idade": 57.0,
            "peso": 88.0,
            "sexo": "Masculino",
            "altura": 1.70,
            "cor": "Preto",
            "tipo_sanguineo": "A+",
            "pai_id": null,
            "mae_id": null,
            "irmaos_id": []
        },
        {
            "id": "b396a04",
            "primeiro_nome": "Ivonete Firmino",
            "ultimo_nome": "da Silva",
            "data_nascimento": null,
            "idade": 45.0,
            "peso": 75.0,
            "sexo": "Feminino",
            "altura": 1.60,
            "cor": "Branca",
            "tipo_sanguineo": "A+",
            "pai_id": null,
            "mae_id": null,
            "irmaos_id": []
        },
        {
            "id": "b396a03",
            "primeiro_nome": "Laercio",
            "ultimo_nome": "Lima",
            "data_nascimento": null,
            "idade": 70.0,
            "peso": 80.0,
            "sexo": "Masculino",
            "altura": 1.67,
            "cor": "Preto",
            "tipo_sanguineo": "A+",
            "pai_id": null,
            "mae_id": null,
            "irmaos_id": []
        },
        {
            "id": "b396a02",
            "primeiro_nome": "Geisa",
            "ultimo_nome": "Floriano",
            "data_nascimento": null,
            "idade": 58.0,
            "peso": 70.0,
            "sexo": "Feminino",
            "altura": 1.60,
            "cor": "Parda",
            "tipo_sanguineo": "A+",
            "pai_id": null,
            "mae_id": null,
            "irmaos_id": []
        }
    ],
    "palavras": [
        {
            "id": 0,
            "profile-id": 0,
            "palavra": "mama",
            "traducao": "mamãe",
            "pronuncia": "má-má",
            "audio": "58e03161-5db6-4cd2-b91b-f2b11e20440d.mp3"
        },
        {
            "id": 1,
            "profile-id": 0,
            "palavra": "cavitá",
            "traducao": "chave",
            "pronuncia": "cá-ví-tá",
            "audio": "58e03161-5db6-4cd2-b91b-f2b11e20440d.mp3"
        }
    ]
}